__init__.py
cstreet.py
cstreet-1.1.2.data/scripts/CStreet
cstreet-1.1.2.dist-info/METADATA
cstreet-1.1.2.dist-info/WHEEL
cstreet-1.1.2.dist-info/top_level.txt
cstreet-1.1.2.dist-info/RECORD
