Metadata-Version: 2.1
Name: cstreet
Version: 1.1.2
Summary: CStreet is a python script (python 3.6, 3.7 or 3.8) for cell state trajectory construction by using k-nearest neighbors graph algorithm for time-series single-cell RNA-seq data.
Home-page: https://github.com/yw-Hua/CStreet
Author: Yuwei Hua
Author-email: ywhua@tongji.edu.com
License: UNKNOWN
Platform: UNKNOWN
Classifier: Development Status :: 5 - Production/Stable
Classifier: Intended Audience :: Developers
Classifier: Topic :: Software Development :: Build Tools
Classifier: License :: OSI Approved :: MIT License
Classifier: Programming Language :: Python :: 3.6
Requires-Python: >=3.6, <3.9
Requires-Dist: pandas (==0.25.3)
Requires-Dist: numpy (>=1.17)
Requires-Dist: scanpy (==1.5.0)
Requires-Dist: anndata (==0.7.2)
Requires-Dist: networkx (==2.4)
Requires-Dist: colorama (>=0.3.9)
Requires-Dist: fa2
Requires-Dist: retrying
Requires-Dist: python-igraph
Requires-Dist: louvain
